iisy/__init__.py
iisy/context_window.py
iisy/run_pipeline.py
iisy/transcription_display.py
iisy/pipeline/__init__.py
iisy/pipeline/asr_pipeline.py
iisy/pipeline/audio.py
iisy/pipeline/pipeline_step.py
iisy/pipeline/speaker_identification_step.py
iisy/pipeline/speech_enhancement_step.py
iisy/pipeline/speech_separation_step.py
iisy/pipeline/speech_transcription_step.py
iisy_asr_pipeline-1.0.3.dist-info/METADATA
iisy_asr_pipeline-1.0.3.dist-info/WHEEL
iisy_asr_pipeline-1.0.3.dist-info/top_level.txt
iisy_asr_pipeline-1.0.3.dist-info/RECORD
