Metadata-Version: 2.4
Name: iisy-asr-pipeline
Version: 1.0.3
Summary: ASR pipeline for the ASR project
Author-email: Paul Roloff <paul.roloff@uni-bielefeld.de>, Felix Hostert <felix.hostert@uni-bielefeld.de>, Kai Titgens <kai.titgens@uni-bielefeld.de>
Requires-Python: >=3.11.10
Requires-Dist: appdirs==1.4.4
Requires-Dist: asttokens==3.0.0
Requires-Dist: av==14.3.0
Requires-Dist: Bottleneck==1.4.2
Requires-Dist: certifi==2025.1.31
Requires-Dist: cffi==1.17.1
Requires-Dist: charset-normalizer==3.4.1
Requires-Dist: colorama==0.4.6
Requires-Dist: coloredlogs==15.0.1
Requires-Dist: colorlog==6.9.0
Requires-Dist: comm==0.1.4
Requires-Dist: contourpy==1.3.1
Requires-Dist: ctranslate2==4.6.0
Requires-Dist: cycler==0.12.1
Requires-Dist: Cython==3.0.12
Requires-Dist: debugpy==1.8.0
Requires-Dist: decorator==5.1.1
Requires-Dist: DeepFilterLib==0.5.6
Requires-Dist: DeepFilterNet==0.5.6
Requires-Dist: denoiser==0.1.5
Requires-Dist: exceptiongroup==1.2.2
Requires-Dist: executing==2.1.0
Requires-Dist: speechbrain==1.0.2
Requires-Dist: faster-whisper==1.1.1
Requires-Dist: filelock==3.13.1
Requires-Dist: flatbuffers==25.2.10
Requires-Dist: fonttools==4.56.0
Requires-Dist: fsspec==2024.6.1
Requires-Dist: future==1.0.0
Requires-Dist: huggingface-hub==0.29.1
Requires-Dist: humanfriendly==10.0
Requires-Dist: hydra-colorlog==0.1.4
Requires-Dist: hydra-core==0.11.3
Requires-Dist: HyperPyYAML==1.2.2
Requires-Dist: idna==3.10
Requires-Dist: importlib_metadata==8.6.1
Requires-Dist: ipykernel==6.25.2
Requires-Dist: ipython==8.32.0
Requires-Dist: jedi==0.19.2
Requires-Dist: Jinja2==3.1.4
Requires-Dist: joblib==1.4.2
Requires-Dist: julius==0.2.7
Requires-Dist: jupyter_client==8.4.0
Requires-Dist: jupyter_core==5.4.0
Requires-Dist: kiwisolver==1.4.8
Requires-Dist: llvmlite==0.44.0
Requires-Dist: loguru==0.7.3
Requires-Dist: markdown-it-py==3.0.0
Requires-Dist: MarkupSafe==2.1.5
Requires-Dist: matplotlib==3.10.0
Requires-Dist: matplotlib-inline==0.1.7
Requires-Dist: mdurl==0.1.2
Requires-Dist: mkl_fft==1.3.11
Requires-Dist: mkl_random==1.2.8
Requires-Dist: mkl-service==2.4.1
Requires-Dist: more-itertools==10.6.0
Requires-Dist: mpmath==1.3.0
Requires-Dist: nest_asyncio==1.6.0
Requires-Dist: networkx==3.3
Requires-Dist: numba==0.61.0
Requires-Dist: numexpr==2.10.1
Requires-Dist: numpy==1.26.4
Requires-Dist: omegaconf==1.4.1
Requires-Dist: onnxruntime==1.21.0
Requires-Dist: packaging==23.2
Requires-Dist: pandas==2.2.3
Requires-Dist: parso==0.8.4
Requires-Dist: pesq==0.0.4
Requires-Dist: pickleshare==0.7.5
Requires-Dist: pillow==11.0.0
Requires-Dist: pip==25.0.1
Requires-Dist: platformdirs==3.11.0
Requires-Dist: prompt_toolkit==3.0.50
Requires-Dist: protobuf==6.30.2
Requires-Dist: psutil==6.1.1
Requires-Dist: pure_eval==0.2.3
Requires-Dist: PyAudio==0.2.14
Requires-Dist: pybind11==2.13.6
Requires-Dist: pycparser==2.22
Requires-Dist: pydub==0.25.1
Requires-Dist: Pygments==2.19.1
Requires-Dist: pyparsing==3.2.1
Requires-Dist: pyreadline3==3.5.4
Requires-Dist: PySoundFile==0.9.0.post1
Requires-Dist: pystoi==0.4.1
Requires-Dist: python-dateutil==2.9.0.post0
Requires-Dist: pytz==2024.1
Requires-Dist: pywin32==306
Requires-Dist: PyYAML==6.0.2
Requires-Dist: pyzmq==25.1.1
Requires-Dist: regex==2024.11.6
Requires-Dist: requests==2.32.3
Requires-Dist: rich==14.0.0
Requires-Dist: ruamel.yaml==0.18.10
Requires-Dist: ruamel.yaml.clib==0.2.12
Requires-Dist: scikit-learn==1.6.1
Requires-Dist: scipy==1.15.2
Requires-Dist: seaborn==0.13.2
Requires-Dist: sentencepiece==0.2.0
Requires-Dist: setuptools==75.8.0
Requires-Dist: six==1.17.0
Requires-Dist: sounddevice==0.5.1
Requires-Dist: speechbrain==1.0.2
Requires-Dist: stack_data==0.6.3
Requires-Dist: sympy==1.13.1
Requires-Dist: threadpoolctl==3.6.0
Requires-Dist: tiktoken==0.9.0
Requires-Dist: tokenizers==0.21.1
Requires-Dist: torch==2.6.0+cu124
Requires-Dist: torchaudio==2.6.0+cu124
Requires-Dist: tornado==6.3.3
Requires-Dist: tqdm==4.67.1
Requires-Dist: traitlets==5.14.3
Requires-Dist: typing_extensions==4.12.2
Requires-Dist: tzdata==2023.3
Requires-Dist: urllib3==2.3.0
Requires-Dist: wcwidth==0.2.13
Requires-Dist: wheel==0.45.1
Requires-Dist: win32_setctime==1.2.0
Requires-Dist: zipp==3.21.0
